[{"uid":"blt5565c95f39807063","content_type":"image/svg+xml","file_size":"26826","tags":[],"filename":"business-with-al.svg","url":"https://images.contentstack.io/v3/assets/<api_key>/<asset_uid>/<entity_uid>/<asset_name>","ACL":{},"is_dir":false,"parent_uid":"bltfcbe6f1af9fff456","_version":1,"title":"Business With Al","description":"","publish_details":[{"environment":"blt37a5d3280ca7d398","locale":"fr-fr","time":"2022-02-21T05:56:43.058Z","version":1},{"environment":"bltb9d8c6b0b2cf6ea4","locale":"fr-fr","time":"2022-02-21T05:56:43.061Z","version":1},{"environment":"bltfd7f249ca55fdd81","locale":"fr-fr","time":"2022-02-21T05:56:43.064Z","version":1},{"environment":"blt37a5d3280ca7d398","locale":"en-us","time":"2022-02-21T05:56:43.068Z","version":1},{"environment":"bltb9d8c6b0b2cf6ea4","locale":"en-us","time":"2022-02-21T05:56:43.071Z","version":1},{"environment":"bltfd7f249ca55fdd81","locale":"en-us","time":"2022-02-21T05:56:43.074Z","version":1}]}]